{
  "coid": "AZ",
  "cities": [
    {
      "id": "baku",
      "name": "Baku"
    },
    {
      "id": "nakhchivan",
      "name": "Nakhchivan"
    },
    {
      "id": "quba",
      "name": "Quba"
    },
    {
      "id": "qusar",
      "name": "Qusar"
    },
    {
      "id": "sulutapa",
      "name": "Sulutapa"
    },
    {
      "id": "sumqayit",
      "name": "Sumqayit"
    },
    {
      "id": "xirdalan",
      "name": "Xirdalan"
    },
    {
      "id": "zurges",
      "name": "Zurges"
    }
  ]
}