{
  "coid": "BH",
  "cities": [
    {
      "name": "Al Budayyi`",
      "id": "q-af662P9qXq"
    },
    {
      "name": "Al Hadd",
      "id": "kQ6vgA9Sl1rq"
    },
    {
      "name": "Al Hamalah",
      "id": "ku2-rYeiHg-s"
    },
    {
      "name": "Al Janabiyah",
      "id": "xqWSbj7r2olZ"
    },
    {
      "name": "Al Markh",
      "id": "cXNERWjG-uJo"
    },
    {
      "name": "Al Muharraq",
      "id": "nasM29vzJIg2"
    },
    {
      "name": "Bani Jamrah",
      "id": "AomJf6_xwgxQ"
    },
    {
      "name": "Barbar",
      "id": "_h-XgjXdx1b9"
    },
    {
      "name": "Jurdab",
      "id": "TMYBvDWOaaWl"
    },
    {
      "name": "Madinat `Isa",
      "id": "Ct0B63ccAamN"
    },
    {
      "name": "Madinat Hamad",
      "id": "D-hSYr_zVWHP"
    },
    {
      "name": "Manama",
      "id": "B2IcdZjEEFi-"
    },
    {
      "name": "Oil City",
      "id": "tJGlOEhZmj0a"
    },
    {
      "name": "Sanabis",
      "id": "aJzLo3tFqfa7"
    },
    {
      "name": "Sanad",
      "id": "ijXt10AiLW4_"
    },
    {
      "name": "Sitrah",
      "id": "LrHsWCKjTOS-"
    },
    {
      "name": "Tubli",
      "id": "rtjU69aL786H"
    }
  ]
}