{
  "coid": "PW",
  "cities": [
    {
      "id": "ngerulmud",
      "name": "Ngerulmud"
    },
    {
      "id": "koror",
      "name": "Koror"
    },
    {
      "id": "airai",
      "name": "Airai"
    },
    {
      "id": "melekeok",
      "name": "Melekeok"
    },
    {
      "id": "ngaraard",
      "name": "Ngaraard"
    },
    {
      "id": "ngardmau",
      "name": "Ngardmau"
    },
    {
      "id": "ngchesar",
      "name": "Ngchesar"
    },
    {
      "id": "ngiwal",
      "name": "Ngiwal"
    },
    {
      "id": "peleliu",
      "name": "Peleliu"
    },
    {
      "id": "angaur",
      "name": "Angaur"
    }
  ]
}